pytorch_clip/__init__.py
pytorch_clip/utils.py
pytorch_clip/configs/clip_vit_b16.yml
pytorch_clip/configs/clip_vit_b32.yml
pytorch_clip/configs/ruclip.yml
pytorch_clip/models/__init__.py
pytorch_clip/models/clip.py
pytorch_clip/models/clip_modified.py
pytorch_clip/models/ruclip.py
pytorch_clip/models/utils.py
pytorch_clip/processor/__init__.py
pytorch_clip/processor/image_processor.py
pytorch_clip/processor/text_processor.py
pytorch_clip/processor/utils.py
pytorch_clip-2021.12.21.0.dist-info/LICENSE
pytorch_clip-2021.12.21.0.dist-info/METADATA
pytorch_clip-2021.12.21.0.dist-info/WHEEL
pytorch_clip-2021.12.21.0.dist-info/top_level.txt
pytorch_clip-2021.12.21.0.dist-info/zip-safe
pytorch_clip-2021.12.21.0.dist-info/RECORD
