Metadata-Version: 2.1
Name: pytorch-clip
Version: 2021.12.21.0
Summary: Pytorch API to work with CLIP models.
Home-page: UNKNOWN
Author: Sergei Belousov aka BeS
Author-email: sergei.o.belousov@gmail.com
License: UNKNOWN
Platform: UNKNOWN
Classifier: Programming Language :: Python :: 3
Requires-Dist: Cython
Requires-Dist: cython
Requires-Dist: googletrans
Requires-Dist: huggingface-hub
Requires-Dist: numpy
Requires-Dist: omegaconf
Requires-Dist: torch
Requires-Dist: transformers
Requires-Dist: wheel
Requires-Dist: youtokentome
